filetype_detector/__init__.py
filetype_detector/base_inferencer.py
filetype_detector/inferencer.py
filetype_detector/lexical_inferencer.py
filetype_detector/magic_inferencer.py
filetype_detector/magika_inferencer.py
filetype_detector/mixture_inferencer.py
filetype_detector-0.2.0.dist-info/METADATA
filetype_detector-0.2.0.dist-info/WHEEL
filetype_detector-0.2.0.dist-info/licenses/LICENSE
filetype_detector-0.2.0.dist-info/RECORD
