Metadata-Version: 2.4
Name: filetype-detector
Version: 0.2.0
Summary: A flexible Python library for file type inference using multiple strategies including extension-based, magic number-based, and AI-powered detection
Author-email: devcomfort <im@devcomfort.me>
License: MIT
License-File: LICENSE
Keywords: ai-detection,file-detection,file-type,magic-numbers,mime-type
Classifier: Development Status :: 4 - Beta
Classifier: Intended Audience :: Developers
Classifier: License :: OSI Approved :: MIT License
Classifier: Programming Language :: Python :: 3
Classifier: Programming Language :: Python :: 3.8
Classifier: Programming Language :: Python :: 3.9
Classifier: Programming Language :: Python :: 3.10
Classifier: Programming Language :: Python :: 3.11
Classifier: Programming Language :: Python :: 3.12
Classifier: Topic :: Software Development :: Libraries :: Python Modules
Classifier: Topic :: Utilities
Requires-Python: >=3.8
Requires-Dist: loguru>=0.7.3
Requires-Dist: magika>=1.0.1
Requires-Dist: pytest>=8.4.2
Requires-Dist: python-magic>=0.4.27
Provides-Extra: dev
Requires-Dist: loguru>=0.7.3; extra == 'dev'
Requires-Dist: pytest>=8.4.2; extra == 'dev'
Provides-Extra: docs
Requires-Dist: mkdocs>=1.6.1; extra == 'docs'
Requires-Dist: mkdocstrings[python]>=0.24.0; extra == 'docs'
